rtl/alu.v
module alu (
    input [31:0] a,
    input [31:0] b, 
    input [3:0] alu_control,
    output reg [31:0] result,
    output zero
);

always @(*) begin
    case (alu_control)
        4'b0000: result = a + b;        // ADD
        4'b0001: result = a - b;        // SUB
        4'b0010: result = a & b;        // AND
        4'b0011: result = a | b;        // OR
        4'b0100: result = a ^ b;        // XOR
        4'b0101: result = a << b[4:0];  // SLL
        4'b0110: result = a >> b[4:0];  // SRL
        4'b0111: result = $signed(a) >>> b[4:0]; // SRA
        4'b1000: result = ($signed(a) < $signed(b)) ? 32'h00000001 : 32'h00000000; // SLT (Set Less Than)
        4'b1001: result = (a < b) ? 32'h00000001 : 32'h00000000; // SLTU (Set Less Than Unsigned)
        default: result = 32'h0;
    endcase
end
assign zero = (result == 32'h0);

endmodule

tb/tb_alu.v
// Testbench for ALU Module
// Tests all ALU operations and verifies functionality

`timescale 1ns/1ps

module tb_alu;

// Testbench signals
reg [31:0] a;
reg [31:0] b;
reg [3:0] alu_control;
wire [31:0] result;
wire zero;

// Error tracking
integer error_count = 0;
integer test_count = 0;

// Instantiate ALU
alu uut (
    .a(a),
    .b(b),
    .alu_control(alu_control),
    .result(result),
    .zero(zero)
);

// Task to check results
task check_result;
    input [31:0] expected;
    input [3:0] operation;
    input [31:0] a_val, b_val;
    begin
        test_count = test_count + 1;
        if (result !== expected) begin
            $display("ERROR: Test %d failed", test_count);
            $display("  Operation: %b, A: %d, B: %d", operation, a_val, b_val);
            $display("  Expected: %d, Got: %d", expected, result);
            error_count = error_count + 1;
        end else begin
            $display("PASS: Test %d - Op:%b A:%d B:%d Result:%d", 
                     test_count, operation, a_val, b_val, result);
        end
    end
endtask

// Main test sequence
initial begin
    $dumpfile("waveforms/alu_test.vcd");
    $dumpvars(0, tb_alu);
    
    $display("Starting ALU Tests...");
    $display("=====================");
    
    // Test ADD operation
    a = 32'd15; b = 32'd25; alu_control = 4'b0000;
    #10; check_result(32'd40, alu_control, a, b);
    
    // Test SUB operation
    a = 32'd50; b = 32'd20; alu_control = 4'b0001;
    #10; check_result(32'd30, alu_control, a, b);
    
    // Test AND operation
    a = 32'hFF00FF00; b = 32'h0FF00FF0; alu_control = 4'b0010;
    #10; check_result(32'h0F000F00, alu_control, a, b);
    
    // Test OR operation
    a = 32'hF0F0F0F0; b = 32'h0F0F0F0F; alu_control = 4'b0011;
    #10; check_result(32'hFFFFFFFF, alu_control, a, b);
    
    // Test XOR operation
    a = 32'hAAAAAAAA; b = 32'h55555555; alu_control = 4'b0100;
    #10; check_result(32'hFFFFFFFF, alu_control, a, b);
    
    // Test SLL (Shift Left Logical)
    a = 32'h00000001; b = 32'd4; alu_control = 4'b0101;
    #10; check_result(32'h00000010, alu_control, a, b);
    
    // Test SRL (Shift Right Logical)
    a = 32'h80000000; b = 32'd4; alu_control = 4'b0110;
    #10; check_result(32'h08000000, alu_control, a, b);
    
    // Test SRA (Shift Right Arithmetic)
    a = 32'h80000000; b = 32'd4; alu_control = 4'b0111;
    #10; check_result(32'hF8000000, alu_control, a, b);
    
    // Test SLT (Set Less Than) - signed
    a = 32'hFFFFFFFF; b = 32'h00000001; alu_control = 4'b1000; // -1 < 1
    #10; check_result(32'h00000001, alu_control, a, b);
    
    // Test SLTU (Set Less Than Unsigned)
    a = 32'hFFFFFFFF; b = 32'h00000001; alu_control = 4'b1001; // 0xFFFFFFFF > 1
    #10; check_result(32'h00000000, alu_control, a, b);
    
    // Test Zero Flag
    a = 32'd5; b = 32'd5; alu_control = 4'b0001; // 5 - 5 = 0
    #10;
    if (zero !== 1'b1) begin
        $display("ERROR: Zero flag should be 1 when result is 0");
        error_count = error_count + 1;
    end else begin
        $display("PASS: Zero flag correctly set");
    end
    
    // Edge cases
    $display("\nTesting Edge Cases...");
    
    // Maximum values
    a = 32'hFFFFFFFF; b = 32'h00000001; alu_control = 4'b0000;
    #10; // This will overflow, just check it doesn't crash
    
    // Zero operands
    a = 32'h00000000; b = 32'h00000000; alu_control = 4'b0011;
    #10; check_result(32'h00000000, alu_control, a, b);
    
    // Test Summary
    $display("\n=====================");
    $display("Test Summary:");
    $display("Total Tests: %d", test_count);
    $display("Errors: %d", error_count);
    
    if (error_count == 0) begin
        $display("ALL TESTS PASSED!");
    end else begin
        $display("SOME TESTS FAILED!");
    end
    
    $display("Simulation completed at time: %t", $time);
    $finish;
end

endmodule

waveforms/alu_test.vcd
$date
	Fri Jun 27 12:07:57 2025
$end
$version
	Icarus Verilog
$end
$timescale
	1ps
$end
$scope module tb_alu $end
$var wire 1 ! zero $end
$var wire 32 " result [31:0] $end
$var reg 32 # a [31:0] $end
$var reg 4 $ alu_control [3:0] $end
$var reg 32 % b [31:0] $end
$var integer 32 & error_count [31:0] $end
$var integer 32 ' test_count [31:0] $end
$scope module uut $end
$var wire 32 ( a [31:0] $end
$var wire 4 ) alu_control [3:0] $end
$var wire 32 * b [31:0] $end
$var wire 1 ! zero $end
$var reg 32 + result [31:0] $end
$upscope $end
$scope task check_result $end
$var reg 32 , a_val [31:0] $end
$var reg 32 - b_val [31:0] $end
$var reg 32 . expected [31:0] $end
$var reg 4 / operation [3:0] $end
$upscope $end
$upscope $end
$enddefinitions $end
$comment Show the parameter values. $end
$dumpall
$end
#0
$dumpvars
bx /
bx .
bx -
bx ,
b101000 +
b11001 *
b0 )
b1111 (
b0 '
b0 &
b11001 %
b0 $
b1111 #
b101000 "
0!
$end
#10000
b11110 "
b11110 +
b1 $
b1 )
b10100 %
b10100 *
b110010 #
b110010 (
b1 '
b11001 -
b1111 ,
b0 /
b101000 .
#20000
b1111000000000000111100000000 "
b1111000000000000111100000000 +
b10 $
b10 )
b1111111100000000111111110000 %
b1111111100000000111111110000 *
b11111111000000001111111100000000 #
b11111111000000001111111100000000 (
b10 '
b10100 -
b110010 ,
b1 /
b11110 .
#30000
b11111111111111111111111111111111 "
b11111111111111111111111111111111 +
b11 $
b11 )
b1111000011110000111100001111 %
b1111000011110000111100001111 *
b11110000111100001111000011110000 #
b11110000111100001111000011110000 (
b11 '
b1111111100000000111111110000 -
b11111111000000001111111100000000 ,
b10 /
b1111000000000000111100000000 .
#40000
b100 $
b100 )
b1010101010101010101010101010101 %
b1010101010101010101010101010101 *
b10101010101010101010101010101010 #
b10101010101010101010101010101010 (
b100 '
b1111000011110000111100001111 -
b11110000111100001111000011110000 ,
b11 /
b11111111111111111111111111111111 .
#50000
b10000 "
b10000 +
b101 $
b101 )
b100 %
b100 *
b1 #
b1 (
b101 '
b1010101010101010101010101010101 -
b10101010101010101010101010101010 ,
b100 /
#60000
b1000000000000000000000000000 "
b1000000000000000000000000000 +
b110 $
b110 )
b10000000000000000000000000000000 #
b10000000000000000000000000000000 (
b110 '
b100 -
b1 ,
b101 /
b10000 .
#70000
b11111000000000000000000000000000 "
b11111000000000000000000000000000 +
b111 $
b111 )
b111 '
b10000000000000000000000000000000 ,
b110 /
b1000000000000000000000000000 .
#80000
b1 "
b1 +
b1000 $
b1000 )
b1 %
b1 *
b11111111111111111111111111111111 #
b11111111111111111111111111111111 (
b1000 '
b111 /
b11111000000000000000000000000000 .
#90000
1!
b0 "
b0 +
b1001 $
b1001 )
b1001 '
b1 -
b11111111111111111111111111111111 ,
b1000 /
b1 .
#100000
b1 $
b1 )
b101 %
b101 *
b101 #
b101 (
b1010 '
b1001 /
b0 .
#110000
b0 $
b0 )
b1 %
b1 *
b11111111111111111111111111111111 #
b11111111111111111111111111111111 (
#120000
b11 $
b11 )
b0 %
b0 *
b0 #
b0 (
#130000
b1011 '
b0 -
b0 ,
b11 /
