rtl/register_file.v
module register_file (
    input clk,
    input reset,
    input [4:0] read_addr1,
    input [4:0] read_addr2,
    input [4:0] write_addr,
    input [31:0] write_data,
    input write_enable,
    output [31:0] read_data1,
    output [31:0] read_data2
);

    reg [31:0] registers [0:31];
    integer i;

    // Write operation
    always @(posedge clk or posedge reset) begin
        if (reset) begin
            for (i = 0; i < 32; i = i + 1)
                registers[i] <= 32'h0;
        end else if (write_enable && write_addr != 5'h0) begin
            registers[write_addr] <= write_data;
        end
    end

    // Read operations with write forwarding
    assign read_data1 = (read_addr1 == 5'h0) ? 32'h0 : 
                      ((write_enable && (read_addr1 == write_addr)) ? write_data : 
                       registers[read_addr1]);
    
    assign read_data2 = (read_addr2 == 5'h0) ? 32'h0 : 
                      ((write_enable && (read_addr2 == write_addr)) ? write_data : 
                       registers[read_addr2]);

endmodule

tb/tb_register_file.v
`timescale 1ns/1ps

module tb_register_file;

    // Inputs
    reg clk;
    reg reset;
    reg [4:0] read_addr1;
    reg [4:0] read_addr2;
    reg [4:0] write_addr;
    reg [31:0] write_data;
    reg write_enable;

    // Outputs
    wire [31:0] read_data1;
    wire [31:0] read_data2;

    // Instantiate the Unit Under Test (UUT)
    register_file uut (
        .clk(clk),
        .reset(reset),
        .read_addr1(read_addr1),
        .read_addr2(read_addr2),
        .write_addr(write_addr),
        .write_data(write_data),
        .write_enable(write_enable),
        .read_data1(read_data1),
        .read_data2(read_data2)
    );

    // Clock generation
    always #5 clk = ~clk;

    // Test sequence
    initial begin
        // Initialize Inputs
        clk = 0;
        reset = 1;
        read_addr1 = 0;
        read_addr2 = 0;
        write_addr = 0;
        write_data = 0;
        write_enable = 0;

        // Create waveform file
        $dumpfile("waveforms/register_file.vcd");
        $dumpvars(0, tb_register_file);

        // Apply reset
        #10 reset = 0;

        // Test 1: Basic write and read
        $display("Test 1: Basic write and read");
        write_addr = 5'h1; 
        write_data = 32'h12345678; 
        write_enable = 1;
        #10;
        write_enable = 0;
        read_addr1 = 5'h1;
        #5;
        if (read_data1 !== 32'h12345678) $display("Error: Read data1 mismatch");
        else $display("PASS: Basic write/read");

        // Test 2: Write to x0 (should be ignored)
        $display("\nTest 2: Write to x0");
        write_addr = 5'h0;
        write_data = 32'hDEADBEEF;
        write_enable = 1;
        #10;
        write_enable = 0;
        read_addr1 = 5'h0;
        #5;
        if (read_data1 !== 32'h0) $display("Error: x0 was modified");
        else $display("PASS: x0 remains zero");

        // Test 3: Write forwarding
        $display("\nTest 3: Write forwarding");
        write_addr = 5'h2;
        write_data = 32'hABCDEF01;
        write_enable = 1;
        read_addr1 = 5'h2; // Read same address being written
        #5;
        if (read_data1 !== 32'hABCDEF01) $display("Error: Write forwarding failed");
        else $display("PASS: Write forwarding works");

        // Test 4: Simultaneous read/write different registers
        $display("\nTest 4: Simultaneous read/write");
        write_addr = 5'h3;
        write_data = 32'hCAFEBABE;
        write_enable = 1;
        read_addr1 = 5'h1; // Read previous value
        read_addr2 = 5'h3; // Read new value being written
        #5;
        if (read_data1 !== 32'h12345678 || read_data2 !== 32'hCAFEBABE) 
            $display("Error: Simultaneous read/write failed");
        else $display("PASS: Simultaneous read/write works");

        // Finish simulation
        #10 $finish;
    end
    
endmodule

waveforms/register_file.vcd
$date
	Sat Jun 28 12:55:39 2025
$end
$version
	Icarus Verilog
$end
$timescale
	1ps
$end
$scope module tb_register_file $end
$var wire 32 ! read_data2 [31:0] $end
$var wire 32 " read_data1 [31:0] $end
$var reg 1 # clk $end
$var reg 5 $ read_addr1 [4:0] $end
$var reg 5 % read_addr2 [4:0] $end
$var reg 1 & reset $end
$var reg 5 ' write_addr [4:0] $end
$var reg 32 ( write_data [31:0] $end
$var reg 1 ) write_enable $end
$scope module uut $end
$var wire 1 # clk $end
$var wire 5 * read_addr1 [4:0] $end
$var wire 5 + read_addr2 [4:0] $end
$var wire 1 & reset $end
$var wire 5 , write_addr [4:0] $end
$var wire 32 - write_data [31:0] $end
$var wire 1 ) write_enable $end
$var wire 32 . read_data2 [31:0] $end
$var wire 32 / read_data1 [31:0] $end
$var integer 32 0 i [31:0] $end
$upscope $end
$upscope $end
$enddefinitions $end
$comment Show the parameter values. $end
$dumpall
$end
#0
$dumpvars
b100000 0
b0 /
b0 .
b0 -
b0 ,
b0 +
b0 *
0)
b0 (
b0 '
1&
b0 %
b0 $
0#
b0 "
b0 !
$end
#5000
b100000 0
1#
#10000
0#
1)
b10010001101000101011001111000 (
b10010001101000101011001111000 -
b1 '
b1 ,
0&
#15000
1#
#20000
b10010001101000101011001111000 "
b10010001101000101011001111000 /
0#
b1 $
b1 *
0)
#25000
1#
1)
b11011110101011011011111011101111 (
b11011110101011011011111011101111 -
b0 '
b0 ,
#30000
0#
#35000
b0 "
b0 /
1#
b0 $
b0 *
0)
#40000
b10101011110011011110111100000001 "
b10101011110011011110111100000001 /
0#
b10 $
b10 *
1)
b10101011110011011110111100000001 (
b10101011110011011110111100000001 -
b10 '
b10 ,
#45000
b11001010111111101011101010111110 !
b11001010111111101011101010111110 .
b10010001101000101011001111000 "
b10010001101000101011001111000 /
1#
b11 %
b11 +
b1 $
b1 *
b11001010111111101011101010111110 (
b11001010111111101011101010111110 -
b11 '
b11 ,
