rtl/branch_predictor.v
module branch_predictor (
    input clk,
    input reset,
    input [31:0] pc,
    input branch_taken,
    input [31:0] branch_target,
    output reg prediction,
    output [31:0] predicted_pc
);

    // 2-bit saturating counter predictor
    reg [1:0] prediction_state [0:1023];  // 1K-entry prediction table
    
    integer i;
    
    // Initialize prediction table
    initial begin
        for (i = 0; i < 1024; i = i + 1) begin
            prediction_state[i] = 2'b01;  // Weakly not taken
        end
    end
    
    // Make prediction
    always @(*) begin
        prediction = prediction_state[pc[11:2]][1];  // Use MSB as prediction
    end
    
    assign predicted_pc = prediction ? (pc + branch_target) : (pc + 4);
    
    // Update predictor
    always @(posedge clk or posedge reset) begin
        if (reset) begin
            for (i = 0; i < 1024; i = i + 1) begin
                prediction_state[i] <= 2'b01;
            end
        end else begin
            if (branch_taken) begin
                // Increment counter (saturating at 3)
                if (prediction_state[pc[11:2]] != 2'b11) begin
                    prediction_state[pc[11:2]] <= prediction_state[pc[11:2]] + 1;
                end
            end else begin
                // Decrement counter (saturating at 0)
                if (prediction_state[pc[11:2]] != 2'b00) begin
                    prediction_state[pc[11:2]] <= prediction_state[pc[11:2]] - 1;
                end
            end
        end
    end

endmodule

tb/tb_branch_predictor.v
`timescale 1ns/1ps

module tb_branch_predictor;

    // Inputs
    reg clk;
    reg reset;
    reg [31:0] pc;
    reg branch_taken;
    reg [31:0] branch_target;
    
    // Outputs
    wire prediction;
    wire [31:0] predicted_pc;
    
    // Instantiate the Unit Under Test (UUT)
    branch_predictor uut (
        .clk(clk),
        .reset(reset),
        .pc(pc),
        .branch_taken(branch_taken),
        .branch_target(branch_target),
        .prediction(prediction),
        .predicted_pc(predicted_pc)
    );
    
    // Clock generation
    always #5 clk = ~clk;
    
    initial begin
        // Initialize Inputs
        clk = 0;
        reset = 1;
        pc = 0;
        branch_taken = 0;
        branch_target = 0;
        
        // Wait 100 ns for global reset
        #100;
        reset = 0;
        
        // Test 1: Initial prediction (weakly not taken)
        $display("Test 1: Initial prediction");
        pc = 32'h1000;
        #10;
        
        // Test 2: Train predictor to taken
        $display("\nTest 2: Train to taken");
        pc = 32'h1000;
        branch_taken = 1;
        branch_target = 32'h1040;
        #10;
        branch_taken = 0;
        #20;
        
        // Test 3: Check prediction after training
        $display("\nTest 3: Check trained prediction");
        pc = 32'h1000;
        #10;
        
        // Finish simulation
        $display("\nSimulation complete");
        $finish;
    end
    
    initial begin
        $dumpfile("tb_branch_predictor.vcd");
        $dumpvars(0, tb_branch_predictor);
    end

endmodule

waveforms/tb_branch_predictor.vcd
$date
	Sun Jun 29 12:22:57 2025
$end
$version
	Icarus Verilog
$end
$timescale
	1ps
$end
$scope module tb_branch_predictor $end
$var wire 1 ! prediction $end
$var wire 32 " predicted_pc [31:0] $end
$var reg 1 # branch_taken $end
$var reg 32 $ branch_target [31:0] $end
$var reg 1 % clk $end
$var reg 32 & pc [31:0] $end
$var reg 1 ' reset $end
$scope module uut $end
$var wire 1 # branch_taken $end
$var wire 32 ( branch_target [31:0] $end
$var wire 1 % clk $end
$var wire 32 ) pc [31:0] $end
$var wire 1 ' reset $end
$var wire 32 * predicted_pc [31:0] $end
$var reg 1 ! prediction $end
$var integer 32 + i [31:0] $end
$upscope $end
$upscope $end
$enddefinitions $end
$comment Show the parameter values. $end
$dumpall
$end
#0
$dumpvars
b10000000000 +
b100 *
b0 )
b0 (
1'
b0 &
0%
b0 $
0#
b100 "
0!
$end
#5000
b10000000000 +
1%
#10000
0%
#15000
b10000000000 +
1%
#20000
0%
#25000
b10000000000 +
1%
#30000
0%
#35000
b10000000000 +
1%
#40000
0%
#45000
b10000000000 +
1%
#50000
0%
#55000
b10000000000 +
1%
#60000
0%
#65000
b10000000000 +
1%
#70000
0%
#75000
b10000000000 +
1%
#80000
0%
#85000
b10000000000 +
1%
#90000
0%
#95000
b10000000000 +
1%
#100000
b1000000000100 "
b1000000000100 *
0%
b1000000000000 &
b1000000000000 )
0'
#105000
1%
#110000
0%
b1000001000000 $
b1000001000000 (
1#
#115000
1%
#120000
0%
0#
