rtl/mem_stage.v
module mem_stage (
    input clk,
    input reset,
    // From EX stage
    input [31:0] alu_result_in,
    input [31:0] rs2_data_in,
    input [2:0] funct3_in,  // Memory operation type
    input mem_read_in,
    input mem_write_in,
    // To WB stage
    output reg [31:0] alu_result_out,
    output reg [31:0] mem_data_out,
    output reg mem_valid,
    // Memory interface
    output [31:0] mem_address,
    output [31:0] mem_write_data,
    output mem_read_req,
    output mem_write_req,
    input [31:0] mem_read_data,
    input mem_ready
);

    // Data memory
    reg [7:0] dmem [0:1023];  // 1KB data memory (byte-addressable)
    
    // Internal signals
    reg [31:0] loaded_data;
    
    // Memory interface
    assign mem_address = alu_result_in;
    assign mem_write_data = rs2_data_in;
    assign mem_read_req = mem_read_in;
    assign mem_write_req = mem_write_in;
    
    // Load operations
    always @(*) begin
        case (funct3_in)
            3'b000: loaded_data = {{24{dmem[alu_result_in[9:0]][7]}}, dmem[alu_result_in[9:0]]};  // LB
            3'b001: loaded_data = {{16{dmem[alu_result_in[9:0]+1][7]}}, dmem[alu_result_in[9:0]+1], dmem[alu_result_in[9:0]]};  // LH
            3'b010: loaded_data = {dmem[alu_result_in[9:0]+3], dmem[alu_result_in[9:0]+2], 
                                 dmem[alu_result_in[9:0]+1], dmem[alu_result_in[9:0]]};  // LW
            3'b100: loaded_data = {24'h0, dmem[alu_result_in[9:0]]};  // LBU
            3'b101: loaded_data = {16'h0, dmem[alu_result_in[9:0]+1], dmem[alu_result_in[9:0]]};  // LHU
            default: loaded_data = 32'h0;
        endcase
    end
    
    // Store operations
    always @(posedge clk) begin
        if (mem_write_in && mem_ready) begin
            case (funct3_in)
                3'b000: begin  // SB
                    dmem[alu_result_in[9:0]] <= rs2_data_in[7:0];
                end
                3'b001: begin  // SH
                    dmem[alu_result_in[9:0]] <= rs2_data_in[7:0];
                    dmem[alu_result_in[9:0]+1] <= rs2_data_in[15:8];
                end
                3'b010: begin  // SW
                    dmem[alu_result_in[9:0]] <= rs2_data_in[7:0];
                    dmem[alu_result_in[9:0]+1] <= rs2_data_in[15:8];
                    dmem[alu_result_in[9:0]+2] <= rs2_data_in[23:16];
                    dmem[alu_result_in[9:0]+3] <= rs2_data_in[31:24];
                end
            endcase
        end
    end
    
    // Pipeline register
    always @(posedge clk or posedge reset) begin
        if (reset) begin
            alu_result_out <= 32'h0;
            mem_data_out <= 32'h0;
            mem_valid <= 1'b0;
        end else begin
            alu_result_out <= alu_result_in;
            mem_data_out <= mem_read_in ? loaded_data : 32'h0;
            mem_valid <= 1'b1;
        end
    end

endmodule

tb/tb_mem_stage.v
`timescale 1ns/1ps

module tb_mem_stage;

    // Inputs
    reg clk;
    reg reset;
    reg [31:0] alu_result_in;
    reg [31:0] rs2_data_in;
    reg [2:0] funct3_in;
    reg mem_read_in;
    reg mem_write_in;
    reg [31:0] mem_read_data;
    reg mem_ready;
    
    // Outputs
    wire [31:0] alu_result_out;
    wire [31:0] mem_data_out;
    wire mem_valid;
    wire [31:0] mem_address;
    wire [31:0] mem_write_data;
    wire mem_read_req;
    wire mem_write_req;
    
    // Instantiate the Unit Under Test (UUT)
    mem_stage uut (
        .clk(clk),
        .reset(reset),
        .alu_result_in(alu_result_in),
        .rs2_data_in(rs2_data_in),
        .funct3_in(funct3_in),
        .mem_read_in(mem_read_in),
        .mem_write_in(mem_write_in),
        .alu_result_out(alu_result_out),
        .mem_data_out(mem_data_out),
        .mem_valid(mem_valid),
        .mem_address(mem_address),
        .mem_write_data(mem_write_data),
        .mem_read_req(mem_read_req),
        .mem_write_req(mem_write_req),
        .mem_read_data(mem_read_data),
        .mem_ready(mem_ready)
    );
    
    // Clock generation
    always #5 clk = ~clk;
    
    initial begin
        // Initialize Inputs
        clk = 0;
        reset = 1;
        alu_result_in = 0;
        rs2_data_in = 0;
        funct3_in = 0;
        mem_read_in = 0;
        mem_write_in = 0;
        mem_read_data = 0;
        mem_ready = 0;
        
        // Wait 100 ns for global reset
        #100;
        reset = 0;
        
        // Test 1: LW operation
        $display("Test 1: LW operation");
        alu_result_in = 32'h100;
        mem_read_data = 32'h12345678;
        mem_read_in = 1;
        funct3_in = 3'b010; // LW
        #10;
        mem_ready = 1;
        #10;
        mem_read_in = 0;
        mem_ready = 0;
        #20;
        
        // Test 2: SW operation
        $display("\nTest 2: SW operation");
        alu_result_in = 32'h104;
        rs2_data_in = 32'h89ABCDEF;
        mem_write_in = 1;
        funct3_in = 3'b010; // SW
        #10;
        mem_ready = 1;
        #10;
        mem_write_in = 0;
        mem_ready = 0;
        #20;
        
        // Test 3: LB operation with sign extension
        $display("\nTest 3: LB operation");
        alu_result_in = 32'h108;
        mem_read_data = 32'h000000F0;
        mem_read_in = 1;
        funct3_in = 3'b000; // LB
        #10;
        mem_ready = 1;
        #10;
        mem_read_in = 0;
        mem_ready = 0;
        #20;
        
        // Finish simulation
        $display("\nSimulation complete");
        $finish;
    end
    
    initial begin
        $dumpfile("tb_mem_stage.vcd");
        $dumpvars(0, tb_mem_stage);
    end

endmodule

waveforms/tb_mem_stage.vcd
$date
	Sun Jun 29 12:22:58 2025
$end
$version
	Icarus Verilog
$end
$timescale
	1ps
$end
$scope module tb_mem_stage $end
$var wire 1 ! mem_write_req $end
$var wire 32 " mem_write_data [31:0] $end
$var wire 1 # mem_valid $end
$var wire 1 $ mem_read_req $end
$var wire 32 % mem_data_out [31:0] $end
$var wire 32 & mem_address [31:0] $end
$var wire 32 ' alu_result_out [31:0] $end
$var reg 32 ( alu_result_in [31:0] $end
$var reg 1 ) clk $end
$var reg 3 * funct3_in [2:0] $end
$var reg 32 + mem_read_data [31:0] $end
$var reg 1 , mem_read_in $end
$var reg 1 - mem_ready $end
$var reg 1 . mem_write_in $end
$var reg 1 / reset $end
$var reg 32 0 rs2_data_in [31:0] $end
$scope module uut $end
$var wire 32 1 alu_result_in [31:0] $end
$var wire 1 ) clk $end
$var wire 3 2 funct3_in [2:0] $end
$var wire 32 3 mem_address [31:0] $end
$var wire 32 4 mem_read_data [31:0] $end
$var wire 1 , mem_read_in $end
$var wire 1 $ mem_read_req $end
$var wire 1 - mem_ready $end
$var wire 32 5 mem_write_data [31:0] $end
$var wire 1 . mem_write_in $end
$var wire 1 ! mem_write_req $end
$var wire 1 / reset $end
$var wire 32 6 rs2_data_in [31:0] $end
$var reg 32 7 alu_result_out [31:0] $end
$var reg 32 8 loaded_data [31:0] $end
$var reg 32 9 mem_data_out [31:0] $end
$var reg 1 # mem_valid $end
$upscope $end
$upscope $end
$enddefinitions $end
$comment Show the parameter values. $end
$dumpall
$end
#0
$dumpvars
b0 9
bx 8
b0 7
b0 6
b0 5
b0 4
b0 3
b0 2
b0 1
b0 0
1/
0.
0-
0,
b0 +
b0 *
0)
b0 (
b0 '
b0 &
b0 %
0$
0#
b0 "
0!
$end
#5000
1)
#10000
0)
#15000
1)
#20000
0)
#25000
1)
#30000
0)
#35000
1)
#40000
0)
#45000
1)
#50000
0)
#55000
1)
#60000
0)
#65000
1)
#70000
0)
#75000
1)
#80000
0)
#85000
1)
#90000
0)
#95000
1)
#100000
0)
b10 *
b10 2
1$
1,
b10010001101000101011001111000 +
b10010001101000101011001111000 4
b100000000 &
b100000000 3
b100000000 (
b100000000 1
0/
#105000
1#
bx %
bx 9
b100000000 '
b100000000 7
1)
#110000
0)
1-
#115000
1)
#120000
0)
0-
0$
0,
#125000
b0 %
b0 9
1)
#130000
0)
#135000
1)
#140000
0)
1!
1.
b10001001101010111100110111101111 "
b10001001101010111100110111101111 5
b10001001101010111100110111101111 0
b10001001101010111100110111101111 6
b100000100 &
b100000100 3
b100000100 (
b100000100 1
#145000
b100000100 '
b100000100 7
1)
#150000
0)
1-
#155000
b10001001101010111100110111101111 8
1)
#160000
0)
0-
0!
0.
#165000
1)
#170000
0)
#175000
1)
#180000
bx 8
0)
b0 *
b0 2
1$
1,
b11110000 +
b11110000 4
b100001000 &
b100001000 3
b100001000 (
b100001000 1
#185000
bx %
bx 9
b100001000 '
b100001000 7
1)
#190000
0)
1-
#195000
1)
#200000
0)
0-
0$
0,
#205000
b0 %
b0 9
1)
